sammy/__init__.py
sammy/__main__.py
sammy/sammy.py
sammy_sjsu_dev2-0.2.0.dist-info/LICENSE
sammy_sjsu_dev2-0.2.0.dist-info/METADATA
sammy_sjsu_dev2-0.2.0.dist-info/WHEEL
sammy_sjsu_dev2-0.2.0.dist-info/entry_points.txt
sammy_sjsu_dev2-0.2.0.dist-info/top_level.txt
sammy_sjsu_dev2-0.2.0.dist-info/RECORD
