Metadata-Version: 2.1
Name: sammy-sjsu-dev2
Version: 0.2.0
Summary: A tool for managing SJSU-Dev2 firmware projects and to install external packages such as platforms and libraries.
Home-page: https://github.com/SJSU-Dev2/sammy/
Author: SJSU-Dev2 Organization
License: UNKNOWN
Platform: UNKNOWN
Classifier: Programming Language :: Python :: 3
Classifier: License :: OSI Approved :: Apache Software License
Classifier: Operating System :: MacOS :: MacOS X
Classifier: Operating System :: POSIX :: Linux
Requires-Python: >=3.9
License-File: LICENSE
Requires-Dist: click (>=8.0)
Requires-Dist: giturlparse (>=0.10.0)
Requires-Dist: requests (>=2.25.1)
